simple-dedup/__init__.py
simple-dedup/dedup.py
simpleDedup/__init__.py
simpleDedup/dedup.py
simpleDedup-0.1.4.dist-info/METADATA
simpleDedup-0.1.4.dist-info/WHEEL
simpleDedup-0.1.4.dist-info/top_level.txt
simpleDedup-0.1.4.dist-info/RECORD
