Metadata-Version: 2.1
Name: simpleDedup
Version: 0.1.4
Summary: 提供多种简单爬虫url去重
Home-page: UNKNOWN
Author: phimes
Author-email: phimes@163.com
License: UNKNOWN
Platform: UNKNOWN
Requires-Dist: redis (>=4.4.2)
